keras_conv_visualizer/__init__.py
keras_conv_visualizer/filters.py
keras_conv_visualizer/gradcam.py
keras_conv_visualizer/intermediate_activations.py
keras_conv_visualizer-0.0.3.dist-info/LICENSE
keras_conv_visualizer-0.0.3.dist-info/METADATA
keras_conv_visualizer-0.0.3.dist-info/WHEEL
keras_conv_visualizer-0.0.3.dist-info/top_level.txt
keras_conv_visualizer-0.0.3.dist-info/RECORD
