Metadata-Version: 2.1
Name: keras-conv-visualizer
Version: 0.0.3
Summary: Package allows visualize convolutional layers from keras models.
Home-page: https://github.com/albertlis/keras-conv-visualizer
Author: Albert Lis
Author-email: albert.lis.1996@gmail.com
License: UNKNOWN
Platform: UNKNOWN
Classifier: Programming Language :: Python :: 3
Classifier: Programming Language :: Python :: 3.6
Classifier: License :: OSI Approved :: MIT License
Classifier: Operating System :: OS Independent
Requires-Dist: tensorflow (>=2.0)
Requires-Dist: numpy (<=1.19.5,>=1.0)
Requires-Dist: opencv-python (>=4.0)
Requires-Dist: matplotlib (>=3.0)
Requires-Dist: keras (>=2.0)
